bytedance_llm_api_scen_gen/__init__.py
bytedance_llm_api_scen_gen-0.0.1.dist-info/METADATA
bytedance_llm_api_scen_gen-0.0.1.dist-info/WHEEL
bytedance_llm_api_scen_gen-0.0.1.dist-info/top_level.txt
bytedance_llm_api_scen_gen-0.0.1.dist-info/RECORD
