Metadata-Version: 2.1
Name: bytedance-llm-api-scen-gen
Version: 0.0.1
Summary: A simple package named bytedance_llm_api_scen_gen
Home-page: https://github.com/artifact/bytedance_llm_api_scen_gen.git
Author: artifact
Author-email: artifact@example.com
License: UNKNOWN
Platform: UNKNOWN
Classifier: Programming Language :: Python :: 3
Classifier: License :: OSI Approved :: MIT License
Classifier: Operating System :: OS Independent
